{
  "name": {
    "mr": "चि.  सौरभ महादेव गायकवाड",
    "en": "Mr. Saurabh Mahadev Gaikwad"
  },
  "personal": {
    "dob": {
      "mr": "१३ ऑक्टोबर १९९९",
      "en": "13 October 1999"
    },
    "height": {
      "mr": "५  फूट २  इंच (१५६ cm)",
      "en": "5 ft 2 in (156 cm)"
    },
    "colour": {
      "mr": "गोरा",
      "en": "Fair"
    },
    "jatDharma": {
      "mr": "मराठा / हिंदू",
      "en": "Maratha / Hindu"
    },
    "kuldaivat": {
      "mr": "श्री. काळ भैरवनाथ",
      "en": "Shri Kal Bhairavnath"
    },
    "devak": {
      "mr": "सूर्यकिरण",
      "en": "Suryakiran"
    },
    "bloodGroup": {
      "mr": "अ +",
      "en": "A+"
    }
  },
  "horoscope": {
    "gan": {
      "mr": "देव गण",
      "en": "Dev Gan"
    },
    "nadi": {
      "mr": "मध्य  नाडी",
      "en": "Madhy Nadi"
    },
    "janmanakshatra": {
      "mr": "अनुराधा",
      "en": "Anuradha"
    },
    "jamvel": {
      "mr": "दुपारी  ०२ :४२",
      "en": "Aftenoon  02 : 42"
    }
  },
  "education": {
    "qualification": {
      "mr": "B.E. ( मेकॅनिकल इंजीनियर )",
      "en": "B.E. (Mechanical  Engineering)"
    },
    "college": {
      "mr": "शासकीय अभियांत्रिकी व संशोधन महाविद्यालय (अवसरी, पुणे)",
      "en": "Government College of Engineering and Research, Avasari Khurd"
    },
    "passingYear": {
      "mr": "2018-2022",
      "en": "2018-2022"
    }
  },
  "career": {
    "company": {
      "mr": "G Square Techsystems Pvt. Ltd.",
      "en": "G Square Techsystems Pvt. Ltd."
    },
    "designation": {
      "mr": "डिजाइन इंजीनियर",
      "en": "Design Engineer"
    },
    "salary": {
      "mr": "₹ 5,50,000 / वार्षिक",
      "en": "₹ 5,50,000 / Annually"
    }
  },
  "family": {
    "father": {
      "name": {
        "mr": "श्री. महादेव श्रीरंग गायकवाड",
        "en": "Shri. Mahadev Shrirang Gaikwad"
      },
      "occupation": {
        "mr": "शेती व्यवसाय",
        "en": "Farming"
      }
    },
    "mother": {
      "name": {
        "mr": "सौ. वंदना महादेव गायकवाड",
        "en": "Sau. Vandana Mahadev गायकवाड"
      },
      "occupation": {
        "mr": "गृहिणी",
        "en": "Homemaker"
      }
    },
    "sisters": [
      {
        "name": {
          "mr": "सौ. अश्विनी रामचंद्र भोसले",
          "en": "Ashwini Ramchandra Bhosale"
        },
        "occupation": {
          "mr": "रोसा",
          "en": "Rosa"
        },
        "married": {
          "mr": "विवाहित",
          "en": "Married"
        }
      },
      {
        "name": {
          "mr": "रोहिणी सौरभ पोळ",
          "en": "Rohini Saurabh Pol"
        },
        "occupation": {
          "mr": "नर्ले",
          "en": "Nerle"
        },
        "married": {
          "mr": "विवहीत",
          "en": "Married"
        }
      }
    ],
    "brothers": [],
    "mamas": [
      {
        "name": {
          "mr": "श्री.रामेश्वर दिगंबर रोडगे",
          "en": "Mr. Rameshwar Digambar Rodage"
        },
        "relation": {
          "mr": "",
          "en": ""
        },
        "location": {
          "mr": "बावची",
          "en": "Bawchi"
        }
      },
      {
        "name": {
          "mr": "श्री.सिद्धेश्वर दिगंबर रोडगे",
          "en": "Mr. Siddheswar  Digamber Rodage"
        },
        "relation": {
          "mr": "",
          "en": ""
        },
        "location": {
          "mr": "बावची",
          "en": "Bawchi"
        }
      }
    ],
    "mushis": [
      {
        "name": {
          "mr": "सौ. चंद्रकला उत्तम गायकवाड",
          "en": "Chandrakala Uttam Gaikwad"
        },
        "relation": {
          "mr": "",
          "en": ""
        },
        "location": {
          "mr": "बुकी",
          "en": "Buki"
        }
      },
      {
        "name": {
          "mr": "सौ. नंदा तुकाराम अंधारे",
          "en": "Nandana Tukaram Andhare"
        },
        "relation": {
          "mr": "",
          "en": ""
        },
        "location": {
          "mr": "भांडगाव",
          "en": "Bhandgaon"
        }
      }
    ],
    "chultas": [
      {
        "name": {
          "mr": "श्री. गौतम गायकवाड",
          "en": "Mr Gautam Gaikwad"
        },
        "occupation": {
          "mr": "",
          "en": ""
        },
        "location": {
          "mr": "",
          "en": ""
        }
      },
      {
        "name": {
          "mr": "श्री.उत्तम गायकवाड",
          "en": "Mr Uttam Gaikwad"
        },
        "occupation": {
          "mr": "",
          "en": ""
        },
        "location": {
          "mr": "",
          "en": ""
        }
      },
      {
        "name": {
          "mr": "श्री.विष्णु गायकवाड",
          "en": "Mr Vishnu Gaikwad"
        },
        "occupation": {
          "mr": "",
          "en": ""
        },
        "location": {
          "mr": "",
          "en": ""
        }
      },
      {
        "name": {
          "mr": "श्री.बाळासाहेब गायकवाड",
          "en": "Mr  Babasaheb Gaikwad"
        },
        "occupation": {
          "mr": "",
          "en": ""
        },
        "location": {
          "mr": "",
          "en": ""
        }
      }
    ]
  },
  "gallery": [],
  "contacts": [
    {
      "name": {
        "mr": "श्री. महादेव  गायकवाड",
        "en": "Mr Mahadev Gaikwad"
      },
      "relation": {
        "mr": "वडील",
        "en": "Father"
      },
      "phone": "9075997060"
    },
    {
      "name": {
        "mr": "सौरभ गायकवाड",
        "en": "Saurabh Gaikwad"
      },
      "relation": {
        "mr": "स्वत",
        "en": "Self"
      },
      "phone": "9689593192"
    }
  ],
  "whatsapp": "919689593192",
  "mapLink": "https://maps.google.com/?q=Pune,Maharashtra",
  "address": {
    "mr": "मु. पो. बुकी  ता. परंडा  जि. धाराशीव   - 410235",
    "en": "At Buki Tal Paranda D. Dharashiv - 410235"
  }
}